rcssscom/__init__.py
rcssscom/gamestate.py
rcssscom/server.py
pyrcssscom_cangyin-0.0.5.dist-info/METADATA
pyrcssscom_cangyin-0.0.5.dist-info/WHEEL
pyrcssscom_cangyin-0.0.5.dist-info/top_level.txt
pyrcssscom_cangyin-0.0.5.dist-info/RECORD
