Metadata-Version: 2.1
Name: pyrcssscom-cangyin
Version: 0.0.5
Summary: simple communication with rcssserver3d server.
Home-page: UNKNOWN
Author: cangyin
Author-email: excangyin@gmail.com
License: UNKNOWN
Platform: UNKNOWN
Classifier: Programming Language :: Python :: 3
Classifier: License :: OSI Approved :: MIT License
Classifier: Operating System :: OS Independent
Requires-Python: >=3.6
Requires-Dist: coloredlog
